[
  {
    "id": 1,
    "difficulty": "easy",
    "image": "https://raw.githubusercontent.com/sarvjeetrawat/rebusimages/main/images/image1.png",
    "question": "What's it called?",
    "answer": "try to understand",
    "hint": "Try to"
  },
  {
    "id": 2,
    "difficulty": "easy",
    "image": "https://raw.githubusercontent.com/sarvjeetrawat/rebusimages/main/images/image2.png",
    "question": "What does this show?",
    "answer": "downtown",
    "hint": "Down"
  },
  {
    "id": 3,
    "difficulty": "easy",
    "image": "https://raw.githubusercontent.com/sarvjeetrawat/rebusimages/main/images/image3.png",
    "question": "What's it called?",
    "answer": "forget it",
    "hint": "Forget"
  },
  {
    "id": 4,
    "difficulty": "easy",
    "image": "https://raw.githubusercontent.com/sarvjeetrawat/rebusimages/main/images/image4.png",
    "question": "What's it called?",
    "answer": "stepfather",
    "hint": "Step"
  },
  {
    "id": 5,
    "difficulty": "easy",
    "image": "https://raw.githubusercontent.com/sarvjeetrawat/rebusimages/main/images/image5.png",
    "question": "What's it called?",
    "answer": "breakfast",
    "hint": "Break"
  },
  {
    "id": 6,
    "difficulty": "medium",
    "image": "https://raw.githubusercontent.com/sarvjeetrawat/rebusimages/main/images/image6.png",
    "question": "What's it called?",
    "answer": "3d movie",
    "hint": "3D"
  },
  {
    "id": 7,
    "difficulty": "medium",
    "image": "https://raw.githubusercontent.com/sarvjeetrawat/rebusimages/main/images/image7.png",
    "question": "What's it called?",
    "answer": "top secret",
    "hint": "Top"
  },
  {
    "id": 8,
    "difficulty": "medium",
    "image": "https://raw.githubusercontent.com/sarvjeetrawat/rebusimages/main/images/image8.png",
    "question": "What's it called?",
    "answer": "metaphor",
    "hint": "Meta"
  },
  {
    "id": 9,
    "difficulty": "medium",
    "image": "https://raw.githubusercontent.com/sarvjeetrawat/rebusimages/main/images/image9.png",
    "question": "What's it called?",
    "answer": "summer",
    "hint": "Sum + R"
  },
  {
    "id": 10,
    "difficulty": "medium",
    "image": "https://raw.githubusercontent.com/sarvjeetrawat/rebusimages/main/images/image10.png",
    "question": "What's it called?",
    "answer": "split level",
    "hint": "Split"
  },
  {
    "id": 11,
    "difficulty": "hard",
    "image": "https://raw.githubusercontent.com/sarvjeetrawat/rebusimages/main/images/image11.png",
    "question": "What's it called?",
    "answer": "travel overseas",
    "hint": "__ + overseas"
  },
  {
    "id": 12,
    "difficulty": "hard",
    "image": "https://raw.githubusercontent.com/sarvjeetrawat/rebusimages/main/images/image12.png",
    "question": "What's it called?",
    "answer": "for once in my life",
    "hint": "For once"
  },
  {
    "id": 13,
    "difficulty": "hard",
    "image": "https://raw.githubusercontent.com/sarvjeetrawat/rebusimages/main/images/image13.png",
    "question": "What's it called?",
    "answer": "but on second thought",
    "hint": "But on second"
  },
  {
    "id": 14,
    "difficulty": "hard",
    "image": "https://raw.githubusercontent.com/sarvjeetrawat/rebusimages/main/images/image14.png",
    "question": "What's it called?",
    "answer": "you are in trouble",
    "hint": "You are"
  },
  {
    "id": 15,
    "difficulty": "hard",
    "image": "https://raw.githubusercontent.com/sarvjeetrawat/rebusimages/main/images/image15.png",
    "question": "What's it called?",
    "answer": "happy hour",
    "hint": "Happy"
  },
  {
    "id": 16,
    "difficulty": "hard",
    "image": "https://raw.githubusercontent.com/sarvjeetrawat/rebusimages/main/images/image16.png",
    "question": "What's it called?",
    "answer": "one in a million",
    "hint": "One in"
  },
  {
    "id": 17,
    "difficulty": "medium",
    "image": "https://raw.githubusercontent.com/sarvjeetrawat/rebusimages/main/images/image17.png",
    "question": "What's it called?",
    "answer": "Engineer",
    "hint": "Engineer"
  },
  {
    "id": 18,
    "difficulty": "easy",
    "image": "https://raw.githubusercontent.com/sarvjeetrawat/rebusimages/main/images/image18.png",
    "question": "What's it called?",
    "answer": "Four wheel drive",
    "hint": "Four Wheel"
  },
  {
    "id": 19,
    "difficulty": "hard",
    "image": "https://raw.githubusercontent.com/sarvjeetrawat/rebusimages/main/images/image19.png",
    "question": "What's it called?",
    "answer": "Robin Hood",
    "hint": "Robin"
  },
  {
    "id": 20,
    "difficulty": "hard",
    "image": "https://raw.githubusercontent.com/sarvjeetrawat/rebusimages/main/images/image20.png",
    "question": "What's it called?",
    "answer": "Vegetables",
    "hint": "Vegetables"
  },
  {
    "id": 21,
    "difficulty": "easy",
    "image": "https://raw.githubusercontent.com/sarvjeetrawat/rebusimages/main/images/image21.png",
    "question": "What's it called?",
    "answer": "Polite",
    "hint": "Polite"
  },
  {
    "id": 22,
    "difficulty": "hard",
    "image": "https://raw.githubusercontent.com/sarvjeetrawat/rebusimages/main/images/image22.png",
    "question": "What's it called?",
    "answer": "long time no see",
    "hint": "long time no see"
  },
  {
    "id": 23,
    "difficulty": "easy",
    "image": "https://raw.githubusercontent.com/sarvjeetrawat/rebusimages/main/images/image23.png",
    "question": "What's it called?",
    "answer": "Apple Pie",
    "hint": "Apple Pie"
  },
  {
    "id": 24,
    "difficulty": "easy",
    "image": "https://raw.githubusercontent.com/sarvjeetrawat/rebusimages/main/images/image24.png",
    "question": "What's it called?",
    "answer": "Up to you",
    "hint": "Up to you"
  },
  {
    "id": 25,
    "difficulty": "easy",
    "image": "https://raw.githubusercontent.com/sarvjeetrawat/rebusimages/main/images/image25.png",
    "question": "What's it called?",
    "answer": "Forehead",
    "hint": "Forehead"
  },
  {
    "id": 26,
    "difficulty": "medium",
    "image": "https://raw.githubusercontent.com/sarvjeetrawat/rebusimages/main/images/image26.png",
    "question": "What's it called?",
    "answer": "Tuna fish",
    "hint": "Tuna fish"
  },
  {
    "id": 27,
    "difficulty": "medium",
    "image": "https://raw.githubusercontent.com/sarvjeetrawat/rebusimages/main/images/image27.png",
    "question": "What's it called?",
    "answer": "Waterfall",
    "hint": "Waterfall"
  },
  {
    "id": 28,
    "difficulty": "easy",
    "image": "https://raw.githubusercontent.com/sarvjeetrawat/rebusimages/main/images/image28.png",
    "question": "What's it called?",
    "answer": "Tea Bag",
    "hint": "Tea"
  },
  {
    "id": 29,
    "difficulty": "easy",
    "image": "https://raw.githubusercontent.com/sarvjeetrawat/rebusimages/main/images/image29.png",
    "question": "What's it called?",
    "answer": "Wake Up",
    "hint": "Wake Up"
  },
  {
    "id": 30,
    "difficulty": "easy",
    "image": "https://raw.githubusercontent.com/sarvjeetrawat/rebusimages/main/images/image30.png",
    "question": "What's it called?",
    "answer": "Miss You",
    "hint": "Miss You"
  },
  {
    "id": 31,
    "difficulty": "easy",
    "image": "https://raw.githubusercontent.com/sarvjeetrawat/rebusimages/main/images/image31.png",
    "question": "What's it called?",
    "answer": "coffee break",
    "hint": "break"
  },
  {
    "id": 32,
    "difficulty": "easy",
    "image": "https://raw.githubusercontent.com/sarvjeetrawat/rebusimages/main/images/image32.png",
    "question": "What's it called?",
    "answer": "split personality",
    "hint": "split"
  },
  {
    "id": 33,
    "difficulty": "medium",
    "image": "https://raw.githubusercontent.com/sarvjeetrawat/rebusimages/main/images/image33.png",
    "question": "What's it called?",
    "answer": "love at first sight",
    "hint": "love at first"
  },
  {
    "id": 34,
    "difficulty": "medium",
    "image": "https://raw.githubusercontent.com/sarvjeetrawat/rebusimages/main/images/image34.png",
    "question": "What's it called?",
    "answer": "twenty four seven",
    "hint": "twenty four seven"
  },
  {
    "id": 35,
    "difficulty": "easy",
    "image": "https://raw.githubusercontent.com/sarvjeetrawat/rebusimages/main/images/image35.png",
    "question": "What's it called?",
    "answer": "potatoes",
    "hint": "potatoes"
  },
  {
    "id": 36,
    "difficulty": "hard",
    "image": "https://raw.githubusercontent.com/sarvjeetrawat/rebusimages/main/images/image36.png",
    "question": "What's it called?",
    "answer": "balanced diet",
    "hint": "balanced"
  },
  {
    "id": 37,
    "difficulty": "hard",
    "image": "https://raw.githubusercontent.com/sarvjeetrawat/rebusimages/main/images/image37.png",
    "question": "What's it called?",
    "answer": "stick around",
    "hint": "Stick around"
  },
  {
    "id": 38,
    "difficulty": "hard",
    "image": "https://raw.githubusercontent.com/sarvjeetrawat/rebusimages/main/images/image38.png",
    "question": "What's it called?",
    "answer": "heavy metal",
    "hint": "heavy metal"
  },
  {
    "id": 39,
    "difficulty": "hard",
    "image": "https://raw.githubusercontent.com/sarvjeetrawat/rebusimages/main/images/image39.png",
    "question": "What's it called?",
    "answer": "raising hell",
    "hint": "raising"
  },
  {
    "id": 40,
    "difficulty": "medium",
    "image": "https://raw.githubusercontent.com/sarvjeetrawat/rebusimages/main/images/image40.png",
    "question": "What's it called?",
    "answer": "scrambled eggs",
    "hint": "scrambled"
  },
  {
    "id": 41,
    "difficulty": "easy",
    "image": "https://raw.githubusercontent.com/sarvjeetrawat/rebusimages/main/images/image41.png",
    "question": "What's it called?",
    "answer": "Up to you",
    "hint": "Up to you"
  },
  {
    "id": 42,
    "difficulty": "hard",
    "image": "https://raw.githubusercontent.com/sarvjeetrawat/rebusimages/main/images/image42.png",
    "question": "What's it called?",
    "answer": "once in a blue moon",
    "hint": "once in a blue moon"
  },
  {
    "id": 43,
    "difficulty": "medium",
    "image": "https://raw.githubusercontent.com/sarvjeetrawat/rebusimages/main/images/image43.png",
    "question": "What's it called?",
    "answer": "Ready for action",
    "hint": "Ready for"
  },
  {
    "id": 45,
    "difficulty": "medium",
    "image": "https://raw.githubusercontent.com/sarvjeetrawat/rebusimages/main/images/image45.png",
    "question": "What's it called?",
    "answer": "misunderstood",
    "hint": "misunderstood"
  },
  {
    "id": 46,
    "difficulty": "medium",
    "image": "https://raw.githubusercontent.com/sarvjeetrawat/rebusimages/main/images/image46.png",
    "question": "What's it called?",
    "answer": "heart attack",
    "hint": "heart attack"
  }
]
